[
{"Text": ["\u0421\u043c\u0430\u0440\u0442\u0444\u043e\u043d SAMSUNG Galaxy A51 4/64 Gb Dual Sim Black (SM-A515FZKUSEK)"], "Site url": "https://www.foxtrot.com.ua/ru/shop/mobilnye_telefony_smartfon.html"},
{"Text": ["\u0421\u043c\u0430\u0440\u0442\u0444\u043e\u043d APPLE iPhone 11 64GB Black (MWLT2RM/A)"], "Site url": "https://www.foxtrot.com.ua/ru/shop/mobilnye_telefony_smartfon.html"},
{"Text": ["\u0421\u043c\u0430\u0440\u0442\u0444\u043e\u043d XIAOMI Redmi Note 8T 4/64GB Dual Sim Starscape Blue"], "Site url": "https://www.foxtrot.com.ua/ru/shop/mobilnye_telefony_smartfon.html"},
{"Text": ["\u0421\u043c\u0430\u0440\u0442\u0444\u043e\u043d HUAWEI P40 Lite E 4/64 Gb Dual Sim Aurora Blue (51095DCG)"], "Site url": "https://www.foxtrot.com.ua/ru/shop/mobilnye_telefony_smartfon.html"},
{"Text": ["\u0421\u043c\u0430\u0440\u0442\u0444\u043e\u043d Samsung Galaxy A71 6/128GB Dual SIM Black (SM-A715FZKUSEK)"], "Site url": "https://www.foxtrot.com.ua/ru/shop/mobilnye_telefony_smartfon.html"},
{"Text": ["\u0421\u043c\u0430\u0440\u0442\u0444\u043e\u043d APPLE iPhone Xs 64GB Space Gray (MT9E2FS/A)"], "Site url": "https://www.foxtrot.com.ua/ru/shop/mobilnye_telefony_smartfon.html"},
{"Text": ["\u0421\u043c\u0430\u0440\u0442\u0444\u043e\u043d XIAOMI Redmi Note 8 Pro 6/64GB Mineral Grey"], "Site url": "https://www.foxtrot.com.ua/ru/shop/mobilnye_telefony_smartfon.html"},
{"Text": ["\u0421\u043c\u0430\u0440\u0442\u0444\u043e\u043d HUAWEI P40 Lite 6/128 Gb Dual Sim Sakura Pink (51095CKA)"], "Site url": "https://www.foxtrot.com.ua/ru/shop/mobilnye_telefony_smartfon.html"},
{"Text": ["\u0421\u043c\u0430\u0440\u0442\u0444\u043e\u043d SAMSUNG Galaxy A10s 2/32 Gb Duos Black (SM-A107FZKDSEK)"], "Site url": "https://www.foxtrot.com.ua/ru/shop/mobilnye_telefony_smartfon.html"},
{"Text": ["\u0421\u043c\u0430\u0440\u0442\u0444\u043e\u043d SAMSUNG Galaxy M21 4/64 Gb Dual Sim Black (SM-M215FZKUSEK)"], "Site url": "https://www.foxtrot.com.ua/ru/shop/mobilnye_telefony_smartfon.html"},
{"Text": ["\u0421\u043c\u0430\u0440\u0442\u0444\u043e\u043d XIAOMI Redmi 8A 2/32 Gb Dual Sim Midnight Black"], "Site url": "https://www.foxtrot.com.ua/ru/shop/mobilnye_telefony_smartfon.html"},
{"Text": ["\u0421\u043c\u0430\u0440\u0442\u0444\u043e\u043d OPPO A9 2020 4/128GB Dual Sim Space Purple"], "Site url": "https://www.foxtrot.com.ua/ru/shop/mobilnye_telefony_smartfon.html"},
{"Text": ["\u0421\u043c\u0430\u0440\u0442\u0444\u043e\u043d APPLE iPhone SE (2 \u043f\u043e\u043a\u043e\u043b\u0435\u043d\u0438\u044f) 64GB Black (MX9R2FS/A)"], "Site url": "https://www.foxtrot.com.ua/ru/shop/mobilnye_telefony_smartfon.html"},
{"Text": ["\u0421\u043c\u0430\u0440\u0442\u0444\u043e\u043d APPLE iPhone 11 Pro Max 64GB Midnight Green (MWHH2FS/A)"], "Site url": "https://www.foxtrot.com.ua/ru/shop/mobilnye_telefony_smartfon.html"},
{"Text": ["\u0421\u043c\u0430\u0440\u0442\u0444\u043e\u043d XIAOMI Redmi 7A 2/32GB Matte Black"], "Site url": "https://www.foxtrot.com.ua/ru/shop/mobilnye_telefony_smartfon.html"},
{"Text": ["\u0421\u043c\u0430\u0440\u0442\u0444\u043e\u043d OPPO A5 2020 3/64GB White"], "Site url": "https://www.foxtrot.com.ua/ru/shop/mobilnye_telefony_smartfon.html"},
{"Text": ["\u0421\u043c\u0430\u0440\u0442\u0444\u043e\u043d Samsung Galaxy M31 6/128GB Black (SM-M315FZKVSEK)"], "Site url": "https://www.foxtrot.com.ua/ru/shop/mobilnye_telefony_smartfon.html"},
{"Text": ["\u0421\u043c\u0430\u0440\u0442\u0444\u043e\u043d APPLE iPhone 7 32Gb Black (MN8X2)"], "Site url": "https://www.foxtrot.com.ua/ru/shop/mobilnye_telefony_smartfon.html"},
{"Text": ["\u0421\u043c\u0430\u0440\u0442\u0444\u043e\u043d XIAOMI Redmi Note 8 4/64GB Space Black"], "Site url": "https://www.foxtrot.com.ua/ru/shop/mobilnye_telefony_smartfon.html"},
{"Text": ["\u0421\u043c\u0430\u0440\u0442\u0444\u043e\u043d HUAWEI P Smart Z 4/64GB Blue"], "Site url": "https://www.foxtrot.com.ua/ru/shop/mobilnye_telefony_smartfon.html"},
{"Text": ["\u0421\u043c\u0430\u0440\u0442\u0444\u043e\u043d XIAOMI Redmi 8 4/64 Gb Dual Sim Onyx Black"], "Site url": "https://www.foxtrot.com.ua/ru/shop/mobilnye_telefony_smartfon.html"},
{"Text": ["\u0421\u043c\u0430\u0440\u0442\u0444\u043e\u043d SAMSUNG Galaxy A51 6/128 Gb Dual Sim Black (SM-A515FZKWSEK)"], "Site url": "https://www.foxtrot.com.ua/ru/shop/mobilnye_telefony_smartfon.html"},
{"Text": ["\u0421\u043c\u0430\u0440\u0442\u0444\u043e\u043d XIAOMI Redmi Note 8 Pro 6/128 Gb Green"], "Site url": "https://www.foxtrot.com.ua/ru/shop/mobilnye_telefony_smartfon.html"},
{"Text": ["\u0421\u043c\u0430\u0440\u0442\u0444\u043e\u043d XIAOMI Redmi Note 8 Pro 6/64GB Blue"], "Site url": "https://www.foxtrot.com.ua/ru/shop/mobilnye_telefony_smartfon.html"},
{"Text": ["\u0421\u043c\u0430\u0440\u0442\u0444\u043e\u043d SAMSUNG Galaxy A51 4/64 Gb Dual Sim Blue (SM-A515FZBUSEK)"], "Site url": "https://www.foxtrot.com.ua/ru/shop/mobilnye_telefony_smartfon.html"},
{"Text": ["\u0421\u043c\u0430\u0440\u0442\u0444\u043e\u043d XIAOMI Redmi Note 8T 4/64GB Dual Sim Moonshadow Grey"], "Site url": "https://www.foxtrot.com.ua/ru/shop/mobilnye_telefony_smartfon.html"}
]